odoo/addons/l10n_it_account_stamp/README.rst
odoo/addons/l10n_it_account_stamp/__init__.py
odoo/addons/l10n_it_account_stamp/__manifest__.py
odoo/addons/l10n_it_account_stamp/data/data.xml
odoo/addons/l10n_it_account_stamp/i18n/it.po
odoo/addons/l10n_it_account_stamp/i18n/l10n_it_account_stamp.pot
odoo/addons/l10n_it_account_stamp/models/__init__.py
odoo/addons/l10n_it_account_stamp/models/company.py
odoo/addons/l10n_it_account_stamp/models/invoice.py
odoo/addons/l10n_it_account_stamp/models/product.py
odoo/addons/l10n_it_account_stamp/models/res_config_settings.py
odoo/addons/l10n_it_account_stamp/readme/CONFIGURE.rst
odoo/addons/l10n_it_account_stamp/readme/CONTRIBUTORS.rst
odoo/addons/l10n_it_account_stamp/readme/DESCRIPTION.rst
odoo/addons/l10n_it_account_stamp/readme/USAGE.rst
odoo/addons/l10n_it_account_stamp/static/description/icon.png
odoo/addons/l10n_it_account_stamp/static/description/index.html
odoo/addons/l10n_it_account_stamp/views/invoice_view.xml
odoo/addons/l10n_it_account_stamp/views/product_view.xml
odoo/addons/l10n_it_account_stamp/views/res_config_settings_view.xml
odoo11_addon_l10n_it_account_stamp-11.0.1.2.0.dist-info/METADATA
odoo11_addon_l10n_it_account_stamp-11.0.1.2.0.dist-info/WHEEL
odoo11_addon_l10n_it_account_stamp-11.0.1.2.0.dist-info/top_level.txt
odoo11_addon_l10n_it_account_stamp-11.0.1.2.0.dist-info/RECORD
