Metadata-Version: 2.1
Name: odoo11-addon-l10n-it-account-stamp
Version: 11.0.1.2.0
Summary: Gestione automatica dell'imposta di bollo
Home-page: https://github.com/OCA/l10n-italy
Author: Ermanno Gnan, Sergio Corato, Enrico Ganzaroli, Agile Business Group, Odoo Community Association (OCA)
Author-email: support@odoo-community.org
License: LGPL-3
Platform: UNKNOWN
Classifier: Programming Language :: Python
Classifier: Framework :: Odoo
Classifier: License :: OSI Approved :: GNU Lesser General Public License v3 (LGPLv3)
Requires-Python: >=2.7, !=3.0.*, !=3.1.*, !=3.2.*, !=3.3.*, !=3.4.*
Requires-Dist: odoo (<11.1dev,>=11.0a)
